uhttp_static.py
uhttp_static-0.1.3.dist-info/LICENSE
uhttp_static-0.1.3.dist-info/METADATA
uhttp_static-0.1.3.dist-info/WHEEL
uhttp_static-0.1.3.dist-info/RECORD
