Metadata-Version: 2.1
Name: uhttp-static
Version: 0.1.3
Summary: Static files support for µHTTP
License: MIT
Author: gus
Author-email: 0x67757300@gmail.com
Requires-Python: >=3.9,<4.0
Classifier: License :: OSI Approved :: MIT License
Classifier: Programming Language :: Python :: 3
Classifier: Programming Language :: Python :: 3.9
Classifier: Programming Language :: Python :: 3.10
Classifier: Programming Language :: Python :: 3.11
Classifier: Programming Language :: Python :: 3.12
Requires-Dist: uhttp (>=1.3.0,<2.0.0)
